wecom_bot_svr/__init__.py
wecom_bot_svr/app.py
wecom_bot_svr/req_msg.py
wecom_bot_svr/req_msg_str.py
wecom_bot_svr/rsp_msg.py
wecom_bot_svr-0.3.3.dist-info/LICENSE
wecom_bot_svr-0.3.3.dist-info/METADATA
wecom_bot_svr-0.3.3.dist-info/WHEEL
wecom_bot_svr-0.3.3.dist-info/top_level.txt
wecom_bot_svr-0.3.3.dist-info/RECORD
