Metadata-Version: 2.2
Name: wecom-bot-svr
Version: 0.3.3
Summary: WeCom Bot Callback Server Simple Framework
Author-email: panzhongxian <panzhongxian0532@gmail.com>
Project-URL: Homepage, https://github.com/easy-wx/wecom-bot-svr
Project-URL: Issues, https://github.com/easy-wx/wecom-bot-svr/issues
Classifier: Programming Language :: Python :: 3
Classifier: License :: OSI Approved :: MIT License
Classifier: Operating System :: OS Independent
Requires-Python: >=3.8
License-File: LICENSE
Requires-Dist: requests>=2.32.3
Requires-Dist: Flask>=3.0.0
Requires-Dist: wx-crypt>=0.0.2
